README.txt
setup.cfg
setup.py
jrtgaussdist/Binomialdistribution.py
jrtgaussdist/Gaussiandistribution.py
jrtgaussdist/Generaldistribution.py
jrtgaussdist/__init__.py
jrtgaussdist.egg-info/PKG-INFO
jrtgaussdist.egg-info/SOURCES.txt
jrtgaussdist.egg-info/dependency_links.txt
jrtgaussdist.egg-info/not-zip-safe
jrtgaussdist.egg-info/top_level.txt