Metadata-Version: 1.0
Name: jrtgaussdist
Version: 0.1
Summary: JRT Gaussian and Binomial distributions
Home-page: UNKNOWN
Author: UNKNOWN
Author-email: UNKNOWN
License: UNKNOWN
Platform: UNKNOWN
